<?xml version="1.0"?>
<ArrayOfParcel xmlns:xsi="http://www.w3.org/2001/XMLSchema-instance" xmlns:xsd="http://www.w3.org/2001/XMLSchema">
  <Parcel>
    <Id>88430</Id>
    <SenderId>61188</SenderId>
    <TargetId>27701</TargetId>
    <DroneId>0</DroneId>
    <priority>Normal</priority>
    <weight>Medium</weight>
    <Requested>2021-01-08T03:45:00</Requested>
    <Scheduled xsi:nil="true" />
    <PickedUp xsi:nil="true" />
    <Delivered xsi:nil="true" />
    <runNumber>0</runNumber>
  </Parcel>
  <Parcel>
    <Id>97867</Id>
    <SenderId>27701</SenderId>
    <TargetId>40491</TargetId>
    <DroneId>0</DroneId>
    <priority>Fast</priority>
    <weight>Light</weight>
    <Requested>2021-11-12T00:44:00</Requested>
    <Scheduled xsi:nil="true" />
    <PickedUp xsi:nil="true" />
    <Delivered xsi:nil="true" />
    <runNumber>0</runNumber>
  </Parcel>
  <Parcel>
    <Id>24454</Id>
    <SenderId>27701</SenderId>
    <TargetId>51257</TargetId>
    <DroneId>0</DroneId>
    <priority>Normal</priority>
    <weight>Medium</weight>
    <Requested>2021-01-09T03:20:00</Requested>
    <Scheduled xsi:nil="true" />
    <PickedUp xsi:nil="true" />
    <Delivered xsi:nil="true" />
    <runNumber>0</runNumber>
  </Parcel>
  <Parcel>
    <Id>60587</Id>
    <SenderId>77168</SenderId>
    <TargetId>13708</TargetId>
    <DroneId>0</DroneId>
    <priority>Normal</priority>
    <weight>Medium</weight>
    <Requested>2021-06-11T01:54:00</Requested>
    <Scheduled xsi:nil="true" />
    <PickedUp xsi:nil="true" />
    <Delivered xsi:nil="true" />
    <runNumber>0</runNumber>
  </Parcel>
  <Parcel>
    <Id>13149</Id>
    <SenderId>27183</SenderId>
    <TargetId>27701</TargetId>
    <DroneId>0</DroneId>
    <priority>Normal</priority>
    <weight>Light</weight>
    <Requested>2021-01-20T00:57:00</Requested>
    <Scheduled xsi:nil="true" />
    <PickedUp xsi:nil="true" />
    <Delivered xsi:nil="true" />
    <runNumber>0</runNumber>
  </Parcel>
  <Parcel>
    <Id>53923</Id>
    <SenderId>77168</SenderId>
    <TargetId>13708</TargetId>
    <DroneId>0</DroneId>
    <priority>Normal</priority>
    <weight>Medium</weight>
    <Requested>2021-05-15T00:25:00</Requested>
    <Scheduled xsi:nil="true" />
    <PickedUp xsi:nil="true" />
    <Delivered xsi:nil="true" />
    <runNumber>0</runNumber>
  </Parcel>
  <Parcel>
    <Id>23187</Id>
    <SenderId>72449</SenderId>
    <TargetId>40491</TargetId>
    <DroneId>0</DroneId>
    <priority>Normal</priority>
    <weight>Light</weight>
    <Requested>2021-09-03T02:21:00</Requested>
    <Scheduled xsi:nil="true" />
    <PickedUp xsi:nil="true" />
    <Delivered xsi:nil="true" />
    <runNumber>0</runNumber>
  </Parcel>
  <Parcel>
    <Id>56346</Id>
    <SenderId>61188</SenderId>
    <TargetId>72449</TargetId>
    <DroneId>0</DroneId>
    <priority>Normal</priority>
    <weight>Light</weight>
    <Requested>2021-05-03T03:57:00</Requested>
    <Scheduled xsi:nil="true" />
    <PickedUp xsi:nil="true" />
    <Delivered xsi:nil="true" />
    <runNumber>0</runNumber>
  </Parcel>
  <Parcel>
    <Id>55594</Id>
    <SenderId>19664</SenderId>
    <TargetId>27701</TargetId>
    <DroneId>0</DroneId>
    <priority>Fast</priority>
    <weight>Medium</weight>
    <Requested>2021-04-21T01:46:00</Requested>
    <Scheduled xsi:nil="true" />
    <PickedUp xsi:nil="true" />
    <Delivered xsi:nil="true" />
    <runNumber>0</runNumber>
  </Parcel>
  <Parcel>
    <Id>27734</Id>
    <SenderId>40491</SenderId>
    <TargetId>12114</TargetId>
    <DroneId>0</DroneId>
    <priority>Fast</priority>
    <weight>Light</weight>
    <Requested>2021-05-25T01:16:00</Requested>
    <Scheduled xsi:nil="true" />
    <PickedUp xsi:nil="true" />
    <Delivered xsi:nil="true" />
    <runNumber>0</runNumber>
  </Parcel>
  <Parcel>
    <Id>59158</Id>
    <SenderId>77168</SenderId>
    <TargetId>27701</TargetId>
    <DroneId>0</DroneId>
    <priority>Fast</priority>
    <weight>Medium</weight>
    <Requested>2021-03-16T02:46:00</Requested>
    <Scheduled xsi:nil="true" />
    <PickedUp xsi:nil="true" />
    <Delivered xsi:nil="true" />
    <runNumber>0</runNumber>
  </Parcel>
  <Parcel>
    <Id>90736</Id>
    <SenderId>61188</SenderId>
    <TargetId>27183</TargetId>
    <DroneId>0</DroneId>
    <priority>Fast</priority>
    <weight>Medium</weight>
    <Requested>2021-10-12T00:49:00</Requested>
    <Scheduled xsi:nil="true" />
    <PickedUp xsi:nil="true" />
    <Delivered xsi:nil="true" />
    <runNumber>0</runNumber>
  </Parcel>
  <Parcel>
    <Id>31245</Id>
    <SenderId>12114</SenderId>
    <TargetId>27701</TargetId>
    <DroneId>0</DroneId>
    <priority>Fast</priority>
    <weight>Light</weight>
    <Requested>2021-05-02T00:57:00</Requested>
    <Scheduled xsi:nil="true" />
    <PickedUp xsi:nil="true" />
    <Delivered xsi:nil="true" />
    <runNumber>0</runNumber>
  </Parcel>
  <Parcel>
    <Id>39993</Id>
    <SenderId>12114</SenderId>
    <TargetId>61188</TargetId>
    <DroneId>0</DroneId>
    <priority>Normal</priority>
    <weight>Light</weight>
    <Requested>2021-11-03T00:02:00</Requested>
    <Scheduled xsi:nil="true" />
    <PickedUp xsi:nil="true" />
    <Delivered xsi:nil="true" />
    <runNumber>0</runNumber>
  </Parcel>
  <Parcel>
    <Id>71958</Id>
    <SenderId>13708</SenderId>
    <TargetId>77168</TargetId>
    <DroneId>0</DroneId>
    <priority>Normal</priority>
    <weight>Medium</weight>
    <Requested>2021-02-14T01:16:00</Requested>
    <Scheduled xsi:nil="true" />
    <PickedUp xsi:nil="true" />
    <Delivered xsi:nil="true" />
    <runNumber>0</runNumber>
  </Parcel>
  <Parcel>
    <Id>96736</Id>
    <SenderId>13708</SenderId>
    <TargetId>40491</TargetId>
    <DroneId>0</DroneId>
    <priority>Fast</priority>
    <weight>Medium</weight>
    <Requested>2021-11-02T01:53:00</Requested>
    <Scheduled xsi:nil="true" />
    <PickedUp xsi:nil="true" />
    <Delivered xsi:nil="true" />
    <runNumber>0</runNumber>
  </Parcel>
  <Parcel>
    <Id>53254</Id>
    <SenderId>19664</SenderId>
    <TargetId>13708</TargetId>
    <DroneId>0</DroneId>
    <priority>Fast</priority>
    <weight>Light</weight>
    <Requested>2021-02-17T02:55:00</Requested>
    <Scheduled xsi:nil="true" />
    <PickedUp xsi:nil="true" />
    <Delivered xsi:nil="true" />
    <runNumber>0</runNumber>
  </Parcel>
  <Parcel>
    <Id>22559</Id>
    <SenderId>27701</SenderId>
    <TargetId>13708</TargetId>
    <DroneId>0</DroneId>
    <priority>Fast</priority>
    <weight>Medium</weight>
    <Requested>2021-01-06T00:29:00</Requested>
    <Scheduled xsi:nil="true" />
    <PickedUp xsi:nil="true" />
    <Delivered xsi:nil="true" />
    <runNumber>0</runNumber>
  </Parcel>
  <Parcel>
    <Id>86536</Id>
    <SenderId>77168</SenderId>
    <TargetId>13708</TargetId>
    <DroneId>0</DroneId>
    <priority>Fast</priority>
    <weight>Medium</weight>
    <Requested>2021-01-28T01:51:00</Requested>
    <Scheduled xsi:nil="true" />
    <PickedUp xsi:nil="true" />
    <Delivered xsi:nil="true" />
    <runNumber>0</runNumber>
  </Parcel>
  <Parcel>
    <Id>67008</Id>
    <SenderId>12114</SenderId>
    <TargetId>27701</TargetId>
    <DroneId>0</DroneId>
    <priority>Normal</priority>
    <weight>Light</weight>
    <Requested>2021-07-14T00:50:00</Requested>
    <Scheduled xsi:nil="true" />
    <PickedUp xsi:nil="true" />
    <Delivered xsi:nil="true" />
    <runNumber>0</runNumber>
  </Parcel>
  <Parcel>
    <Id>22264</Id>
    <SenderId>72449</SenderId>
    <TargetId>40491</TargetId>
    <DroneId>0</DroneId>
    <priority>Normal</priority>
    <weight>Medium</weight>
    <Requested>2021-11-25T02:43:00</Requested>
    <Scheduled xsi:nil="true" />
    <PickedUp xsi:nil="true" />
    <Delivered xsi:nil="true" />
    <runNumber>0</runNumber>
  </Parcel>
  <Parcel>
    <Id>43665</Id>
    <SenderId>27701</SenderId>
    <TargetId>27183</TargetId>
    <DroneId>0</DroneId>
    <priority>Normal</priority>
    <weight>Light</weight>
    <Requested>2021-09-24T01:59:00</Requested>
    <Scheduled xsi:nil="true" />
    <PickedUp xsi:nil="true" />
    <Delivered xsi:nil="true" />
    <runNumber>0</runNumber>
  </Parcel>
  <Parcel>
    <Id>87189</Id>
    <SenderId>19664</SenderId>
    <TargetId>13708</TargetId>
    <DroneId>0</DroneId>
    <priority>Normal</priority>
    <weight>Light</weight>
    <Requested>2021-11-20T03:42:00</Requested>
    <Scheduled xsi:nil="true" />
    <PickedUp xsi:nil="true" />
    <Delivered xsi:nil="true" />
    <runNumber>0</runNumber>
  </Parcel>
  <Parcel>
    <Id>81407</Id>
    <SenderId>72449</SenderId>
    <TargetId>13708</TargetId>
    <DroneId>0</DroneId>
    <priority>Fast</priority>
    <weight>Medium</weight>
    <Requested>2021-02-06T02:04:00</Requested>
    <Scheduled xsi:nil="true" />
    <PickedUp xsi:nil="true" />
    <Delivered xsi:nil="true" />
    <runNumber>0</runNumber>
  </Parcel>
  <Parcel>
    <Id>26122</Id>
    <SenderId>72449</SenderId>
    <TargetId>27183</TargetId>
    <DroneId>0</DroneId>
    <priority>Fast</priority>
    <weight>Medium</weight>
    <Requested>2021-05-29T01:17:00</Requested>
    <Scheduled xsi:nil="true" />
    <PickedUp xsi:nil="true" />
    <Delivered xsi:nil="true" />
    <runNumber>0</runNumber>
  </Parcel>
  <Parcel>
    <Id>43736</Id>
    <SenderId>27183</SenderId>
    <TargetId>40491</TargetId>
    <DroneId>0</DroneId>
    <priority>Normal</priority>
    <weight>Medium</weight>
    <Requested>2021-09-26T02:02:00</Requested>
    <Scheduled xsi:nil="true" />
    <PickedUp xsi:nil="true" />
    <Delivered xsi:nil="true" />
    <runNumber>0</runNumber>
  </Parcel>
  <Parcel>
    <Id>45095</Id>
    <SenderId>27701</SenderId>
    <TargetId>19664</TargetId>
    <DroneId>0</DroneId>
    <priority>Fast</priority>
    <weight>Light</weight>
    <Requested>2021-06-05T01:50:00</Requested>
    <Scheduled xsi:nil="true" />
    <PickedUp xsi:nil="true" />
    <Delivered xsi:nil="true" />
    <runNumber>0</runNumber>
  </Parcel>
  <Parcel>
    <Id>19082</Id>
    <SenderId>27183</SenderId>
    <TargetId>72449</TargetId>
    <DroneId>0</DroneId>
    <priority>Normal</priority>
    <weight>Light</weight>
    <Requested>2021-01-20T02:47:00</Requested>
    <Scheduled xsi:nil="true" />
    <PickedUp xsi:nil="true" />
    <Delivered xsi:nil="true" />
    <runNumber>0</runNumber>
  </Parcel>
  <Parcel>
    <Id>99987</Id>
    <SenderId>72449</SenderId>
    <TargetId>61188</TargetId>
    <DroneId>0</DroneId>
    <priority>Normal</priority>
    <weight>Medium</weight>
    <Requested>2021-06-05T00:35:00</Requested>
    <Scheduled xsi:nil="true" />
    <PickedUp xsi:nil="true" />
    <Delivered xsi:nil="true" />
    <runNumber>0</runNumber>
  </Parcel>
  <Parcel>
    <Id>77637</Id>
    <SenderId>19664</SenderId>
    <TargetId>27701</TargetId>
    <DroneId>0</DroneId>
    <priority>Fast</priority>
    <weight>Medium</weight>
    <Requested>2021-07-26T00:44:00</Requested>
    <Scheduled xsi:nil="true" />
    <PickedUp xsi:nil="true" />
    <Delivered xsi:nil="true" />
    <runNumber>0</runNumber>
  </Parcel>
  <Parcel>
    <Id>99100</Id>
    <SenderId>23724</SenderId>
    <TargetId>72449</TargetId>
    <DroneId>0</DroneId>
    <priority>Normal</priority>
    <weight>Medium</weight>
    <Requested>2021-04-18T01:09:00</Requested>
    <Scheduled xsi:nil="true" />
    <PickedUp xsi:nil="true" />
    <Delivered xsi:nil="true" />
    <runNumber>0</runNumber>
  </Parcel>
  <Parcel>
    <Id>53052</Id>
    <SenderId>46647</SenderId>
    <TargetId>40491</TargetId>
    <DroneId>0</DroneId>
    <priority>Normal</priority>
    <weight>Medium</weight>
    <Requested>2021-08-06T00:14:00</Requested>
    <Scheduled xsi:nil="true" />
    <PickedUp xsi:nil="true" />
    <Delivered xsi:nil="true" />
    <runNumber>0</runNumber>
  </Parcel>
  <Parcel>
    <Id>51319</Id>
    <SenderId>81193</SenderId>
    <TargetId>51257</TargetId>
    <DroneId>0</DroneId>
    <priority>Fast</priority>
    <weight>Light</weight>
    <Requested>2021-07-28T03:50:00</Requested>
    <Scheduled xsi:nil="true" />
    <PickedUp xsi:nil="true" />
    <Delivered xsi:nil="true" />
    <runNumber>0</runNumber>
  </Parcel>
  <Parcel>
    <Id>86108</Id>
    <SenderId>51257</SenderId>
    <TargetId>19664</TargetId>
    <DroneId>0</DroneId>
    <priority>Normal</priority>
    <weight>Light</weight>
    <Requested>2021-10-08T00:33:00</Requested>
    <Scheduled xsi:nil="true" />
    <PickedUp xsi:nil="true" />
    <Delivered xsi:nil="true" />
    <runNumber>0</runNumber>
  </Parcel>
  <Parcel>
    <Id>20598</Id>
    <SenderId>77168</SenderId>
    <TargetId>27183</TargetId>
    <DroneId>0</DroneId>
    <priority>Normal</priority>
    <weight>Medium</weight>
    <Requested>2021-09-21T01:25:00</Requested>
    <Scheduled xsi:nil="true" />
    <PickedUp xsi:nil="true" />
    <Delivered xsi:nil="true" />
    <runNumber>0</runNumber>
  </Parcel>
  <Parcel>
    <Id>90835</Id>
    <SenderId>58442</SenderId>
    <TargetId>77168</TargetId>
    <DroneId>0</DroneId>
    <priority>Normal</priority>
    <weight>Medium</weight>
    <Requested>2021-01-04T01:22:00</Requested>
    <Scheduled xsi:nil="true" />
    <PickedUp xsi:nil="true" />
    <Delivered xsi:nil="true" />
    <runNumber>0</runNumber>
  </Parcel>
  <Parcel>
    <Id>54818</Id>
    <SenderId>61188</SenderId>
    <TargetId>72974</TargetId>
    <DroneId>0</DroneId>
    <priority>Fast</priority>
    <weight>Medium</weight>
    <Requested>2021-11-21T02:40:00</Requested>
    <Scheduled xsi:nil="true" />
    <PickedUp xsi:nil="true" />
    <Delivered xsi:nil="true" />
    <runNumber>0</runNumber>
  </Parcel>
  <Parcel>
    <Id>48589</Id>
    <SenderId>62308</SenderId>
    <TargetId>19664</TargetId>
    <DroneId>0</DroneId>
    <priority>Normal</priority>
    <weight>Light</weight>
    <Requested>2021-11-20T00:42:00</Requested>
    <Scheduled xsi:nil="true" />
    <PickedUp xsi:nil="true" />
    <Delivered xsi:nil="true" />
    <runNumber>0</runNumber>
  </Parcel>
  <Parcel>
    <Id>97404</Id>
    <SenderId>81193</SenderId>
    <TargetId>13708</TargetId>
    <DroneId>0</DroneId>
    <priority>Normal</priority>
    <weight>Medium</weight>
    <Requested>2021-01-20T02:27:00</Requested>
    <Scheduled xsi:nil="true" />
    <PickedUp xsi:nil="true" />
    <Delivered xsi:nil="true" />
    <runNumber>0</runNumber>
  </Parcel>
  <Parcel>
    <Id>87191</Id>
    <SenderId>23724</SenderId>
    <TargetId>77168</TargetId>
    <DroneId>0</DroneId>
    <priority>Normal</priority>
    <weight>Light</weight>
    <Requested>2021-02-18T02:32:00</Requested>
    <Scheduled xsi:nil="true" />
    <PickedUp xsi:nil="true" />
    <Delivered xsi:nil="true" />
    <runNumber>0</runNumber>
  </Parcel>
  <Parcel>
    <Id>64578</Id>
    <SenderId>13708</SenderId>
    <TargetId>19664</TargetId>
    <DroneId>0</DroneId>
    <priority>Normal</priority>
    <weight>Light</weight>
    <Requested>2021-05-10T02:23:00</Requested>
    <Scheduled xsi:nil="true" />
    <PickedUp xsi:nil="true" />
    <Delivered xsi:nil="true" />
    <runNumber>0</runNumber>
  </Parcel>
  <Parcel>
    <Id>93906</Id>
    <SenderId>72974</SenderId>
    <TargetId>72449</TargetId>
    <DroneId>0</DroneId>
    <priority>Fast</priority>
    <weight>Medium</weight>
    <Requested>2021-09-17T01:48:00</Requested>
    <Scheduled xsi:nil="true" />
    <PickedUp xsi:nil="true" />
    <Delivered xsi:nil="true" />
    <runNumber>0</runNumber>
  </Parcel>
  <Parcel>
    <Id>60181</Id>
    <SenderId>51257</SenderId>
    <TargetId>62308</TargetId>
    <DroneId>0</DroneId>
    <priority>Normal</priority>
    <weight>Medium</weight>
    <Requested>2021-08-23T01:16:00</Requested>
    <Scheduled xsi:nil="true" />
    <PickedUp xsi:nil="true" />
    <Delivered xsi:nil="true" />
    <runNumber>0</runNumber>
  </Parcel>
  <Parcel>
    <Id>66066</Id>
    <SenderId>23724</SenderId>
    <TargetId>71376</TargetId>
    <DroneId>0</DroneId>
    <priority>Fast</priority>
    <weight>Light</weight>
    <Requested>2021-10-01T03:26:00</Requested>
    <Scheduled xsi:nil="true" />
    <PickedUp xsi:nil="true" />
    <Delivered xsi:nil="true" />
    <runNumber>0</runNumber>
  </Parcel>
  <Parcel>
    <Id>29823</Id>
    <SenderId>19664</SenderId>
    <TargetId>13708</TargetId>
    <DroneId>0</DroneId>
    <priority>Normal</priority>
    <weight>Medium</weight>
    <Requested>2021-02-21T02:03:00</Requested>
    <Scheduled xsi:nil="true" />
    <PickedUp xsi:nil="true" />
    <Delivered xsi:nil="true" />
    <runNumber>0</runNumber>
  </Parcel>
  <Parcel>
    <Id>21591</Id>
    <SenderId>27183</SenderId>
    <TargetId>72449</TargetId>
    <DroneId>0</DroneId>
    <priority>Fast</priority>
    <weight>Medium</weight>
    <Requested>2021-10-12T01:54:00</Requested>
    <Scheduled xsi:nil="true" />
    <PickedUp xsi:nil="true" />
    <Delivered xsi:nil="true" />
    <runNumber>0</runNumber>
  </Parcel>
  <Parcel>
    <Id>66571</Id>
    <SenderId>44987</SenderId>
    <TargetId>13708</TargetId>
    <DroneId>0</DroneId>
    <priority>Fast</priority>
    <weight>Light</weight>
    <Requested>2021-09-06T00:46:00</Requested>
    <Scheduled xsi:nil="true" />
    <PickedUp xsi:nil="true" />
    <Delivered xsi:nil="true" />
    <runNumber>0</runNumber>
  </Parcel>
  <Parcel>
    <Id>73156</Id>
    <SenderId>19664</SenderId>
    <TargetId>14263</TargetId>
    <DroneId>0</DroneId>
    <priority>Normal</priority>
    <weight>Medium</weight>
    <Requested>2021-02-09T01:25:00</Requested>
    <Scheduled xsi:nil="true" />
    <PickedUp xsi:nil="true" />
    <Delivered xsi:nil="true" />
    <runNumber>0</runNumber>
  </Parcel>
  <Parcel>
    <Id>52925</Id>
    <SenderId>40491</SenderId>
    <TargetId>44987</TargetId>
    <DroneId>0</DroneId>
    <priority>Normal</priority>
    <weight>Light</weight>
    <Requested>2021-04-29T01:44:00</Requested>
    <Scheduled xsi:nil="true" />
    <PickedUp xsi:nil="true" />
    <Delivered xsi:nil="true" />
    <runNumber>0</runNumber>
  </Parcel>
  <Parcel>
    <Id>30133</Id>
    <SenderId>72449</SenderId>
    <TargetId>81193</TargetId>
    <DroneId>0</DroneId>
    <priority>Normal</priority>
    <weight>Light</weight>
    <Requested>2021-08-09T02:00:00</Requested>
    <Scheduled xsi:nil="true" />
    <PickedUp xsi:nil="true" />
    <Delivered xsi:nil="true" />
    <runNumber>0</runNumber>
  </Parcel>
  <Parcel>
    <Id>35772</Id>
    <SenderId>40491</SenderId>
    <TargetId>62308</TargetId>
    <DroneId>0</DroneId>
    <priority>Fast</priority>
    <weight>Medium</weight>
    <Requested>2021-08-18T00:07:00</Requested>
    <Scheduled xsi:nil="true" />
    <PickedUp xsi:nil="true" />
    <Delivered xsi:nil="true" />
    <runNumber>0</runNumber>
  </Parcel>
  <Parcel>
    <Id>85643</Id>
    <SenderId>58442</SenderId>
    <TargetId>46647</TargetId>
    <DroneId>0</DroneId>
    <priority>Fast</priority>
    <weight>Light</weight>
    <Requested>2021-02-13T02:54:00</Requested>
    <Scheduled xsi:nil="true" />
    <PickedUp xsi:nil="true" />
    <Delivered xsi:nil="true" />
    <runNumber>0</runNumber>
  </Parcel>
  <Parcel>
    <Id>26313</Id>
    <SenderId>58442</SenderId>
    <TargetId>40491</TargetId>
    <DroneId>0</DroneId>
    <priority>Normal</priority>
    <weight>Medium</weight>
    <Requested>2021-09-22T01:11:00</Requested>
    <Scheduled xsi:nil="true" />
    <PickedUp xsi:nil="true" />
    <Delivered xsi:nil="true" />
    <runNumber>0</runNumber>
  </Parcel>
  <Parcel>
    <Id>50823</Id>
    <SenderId>58442</SenderId>
    <TargetId>46647</TargetId>
    <DroneId>0</DroneId>
    <priority>Fast</priority>
    <weight>Medium</weight>
    <Requested>2021-10-27T02:49:00</Requested>
    <Scheduled xsi:nil="true" />
    <PickedUp xsi:nil="true" />
    <Delivered xsi:nil="true" />
    <runNumber>0</runNumber>
  </Parcel>
  <Parcel>
    <Id>19698</Id>
    <SenderId>13708</SenderId>
    <TargetId>47663</TargetId>
    <DroneId>0</DroneId>
    <priority>Fast</priority>
    <weight>Medium</weight>
    <Requested>2021-04-19T03:18:00</Requested>
    <Scheduled xsi:nil="true" />
    <PickedUp xsi:nil="true" />
    <Delivered xsi:nil="true" />
    <runNumber>0</runNumber>
  </Parcel>
  <Parcel>
    <Id>26014</Id>
    <SenderId>13708</SenderId>
    <TargetId>14263</TargetId>
    <DroneId>0</DroneId>
    <priority>Normal</priority>
    <weight>Medium</weight>
    <Requested>2021-10-08T01:23:00</Requested>
    <Scheduled xsi:nil="true" />
    <PickedUp xsi:nil="true" />
    <Delivered xsi:nil="true" />
    <runNumber>0</runNumber>
  </Parcel>
  <Parcel>
    <Id>28133</Id>
    <SenderId>61188</SenderId>
    <TargetId>23724</TargetId>
    <DroneId>0</DroneId>
    <priority>Fast</priority>
    <weight>Medium</weight>
    <Requested>2021-05-29T02:36:00</Requested>
    <Scheduled xsi:nil="true" />
    <PickedUp xsi:nil="true" />
    <Delivered xsi:nil="true" />
    <runNumber>0</runNumber>
  </Parcel>
  <Parcel>
    <Id>32069</Id>
    <SenderId>61188</SenderId>
    <TargetId>44987</TargetId>
    <DroneId>0</DroneId>
    <priority>Normal</priority>
    <weight>Medium</weight>
    <Requested>2021-09-01T01:23:00</Requested>
    <Scheduled xsi:nil="true" />
    <PickedUp xsi:nil="true" />
    <Delivered xsi:nil="true" />
    <runNumber>0</runNumber>
  </Parcel>
  <Parcel>
    <Id>82644</Id>
    <SenderId>71376</SenderId>
    <TargetId>44987</TargetId>
    <DroneId>0</DroneId>
    <priority>Normal</priority>
    <weight>Medium</weight>
    <Requested>2021-08-14T00:05:00</Requested>
    <Scheduled xsi:nil="true" />
    <PickedUp xsi:nil="true" />
    <Delivered xsi:nil="true" />
    <runNumber>0</runNumber>
  </Parcel>
  <Parcel>
    <Id>97018</Id>
    <SenderId>62308</SenderId>
    <TargetId>44987</TargetId>
    <DroneId>0</DroneId>
    <priority>Fast</priority>
    <weight>Light</weight>
    <Requested>2021-04-04T02:48:00</Requested>
    <Scheduled xsi:nil="true" />
    <PickedUp xsi:nil="true" />
    <Delivered xsi:nil="true" />
    <runNumber>0</runNumber>
  </Parcel>
</ArrayOfParcel>